upathlib/__init__.py
upathlib/_azure.py
upathlib/_blob.py
upathlib/_gcs.py
upathlib/_local.py
upathlib/_tests.py
upathlib/_upath.py
upathlib/_util.py
upathlib/multiplexer.py
upathlib/py.typed
upathlib/serializer.py
upathlib/versioned_uploadable.py
upathlib-0.9.8.dist-info/LICENSE
upathlib-0.9.8.dist-info/WHEEL
upathlib-0.9.8.dist-info/METADATA
upathlib-0.9.8.dist-info/RECORD
