Metadata-Version: 2.3
Name: upathlib
Version: 0.9.8
Summary: The package *upathlib*
Author-email: Zepu Zhang <zepu.zhang@gmail.com>
Requires-Python: >=3.10
Classifier: Intended Audience :: Developers
Classifier: Programming Language :: Python :: 3
Classifier: Topic :: Software Development :: Libraries :: Python Modules
Requires-Dist: filelock >= 3.9.1
Requires-Dist: deprecation
Requires-Dist: tqdm
Requires-Dist: typing-extensions
Requires-Dist: zstandard
Requires-Dist: azure-storage-blob >=12.9.0,<13.0 ; extra == "abs"
Requires-Dist: sphinx ; extra == "doc"
Requires-Dist: numpydoc ; extra == "doc"
Requires-Dist: pydata-sphinx-theme ; extra == "doc"
Requires-Dist: cloudly[gcp] ; extra == "gcs"
Requires-Dist: google-api-python-client >=2.13.9,<3.0 ; extra == "gcs"
Requires-Dist: google-cloud-storage >=2.0,<3.0 ; extra == "gcs"
Requires-Dist: google-api-core >= 2.12.0 ; extra == "gcs"
Requires-Dist: requests ; extra == "gcs"
Requires-Dist: black ; extra == "test"
Requires-Dist: mypy ; extra == "test"
Requires-Dist: numpy ; extra == "test"
Requires-Dist: pytest-mock ; extra == "test"
Requires-Dist: ruff ; extra == "test"
Requires-Dist: lz4 ; extra == "test"
Requires-Dist: orjson ; extra == "test"
Project-URL: Source, https://github.com/zpz/upathlib
Provides-Extra: abs
Provides-Extra: doc
Provides-Extra: gcs
Provides-Extra: test
